README.rst
scum
scum.py
setup.cfg
setup.py
scum.egg-info/PKG-INFO
scum.egg-info/SOURCES.txt
scum.egg-info/dependency_links.txt
scum.egg-info/requires.txt
scum.egg-info/top_level.txt
src/__init__.py
src/main.py
src/modules/__init__.py
src/modules/browse.py
src/modules/popup.py
src/modules/term.py
src/resources/__init__.py
src/resources/config.txt
src/resources/help.txt
src/resources/start_up.txt
src/resources/tabs.dat