Metadata-Version: 1.1
Name: scum
Version: 0.2.1
Summary: A scummy editor for your terminal!
Home-page: https://github.com/CCareaga/scum
Author: Christian Careaga
Author-email: christian.careaga7@gmail.com
License: UNKNOWN
Download-URL: https://github.com/CCareaga/scum/zipball/v0.2.1
Platform: UNKNOWN
Classifier: License :: OSI Approved :: MIT License
Classifier: Intended Audience :: Developers
Classifier: Programming Language :: Python :: 3
Classifier: Topic :: Utilities
Classifier: Topic :: Text Editors
